{
  "$schema": "https://developer.microsoft.com/json-schemas/fabric/item/report/definition/visualContainer/2.8.0/schema.json",
  "name": "card_rp_undeliverable",
  "position": {
    "x": 390,
    "y": 70,
    "z": 3000,
    "height": 120,
    "width": 370,
    "tabOrder": 3000
  },
  "visual": {
    "visualType": "card",
    "query": {
      "queryState": {
        "Values": {
          "projections": [
            {
              "field": {
                "Measure": {
                  "Expression": {
                    "SourceRef": {
                      "Entity": "data_quality_snapshot"
                    }
                  },
                  "Property": "numerator"
                }
              },
              "queryRef": "data_quality_snapshot.numerator",
              "nativeQueryRef": "numerator"
            }
          ]
        }
      }
    },
    "visualContainerObjects": {
      "title": [
        {
          "properties": {
            "text": {
              "expr": {
                "Literal": {
                  "Value": "'Confirmed Undeliverable Addresses'"
                }
              }
            }
          }
        }
      ]
    },
    "drillFilterOtherVisuals": true
  }
}